{
  "collapse-filter": true,
  "search": "",
  "showTags": false,
  "showAttachments": false,
  "hideUnresolved": false,
  "showOrphans": true,
  "collapse-color-groups": true,
  "colorGroups": [
    {
      "query": "",
      "color": {
        "a": 1,
        "rgb": 14701138
      }
    }
  ],
  "collapse-display": true,
  "showArrow": false,
  "textFadeMultiplier": 0,
  "nodeSizeMultiplier": 1,
  "lineSizeMultiplier": 1,
  "collapse-forces": false,
  "centerStrength": 0.384440104166667,
  "repelStrength": 13.8077799479167,
  "linkStrength": 1,
  "linkDistance": 30,
  "scale": 0.35318771658383913,
  "close": true
}